binary_manager-0.0.7.dist-info/licenses/LICENSE
binman/__init__.py
binman/bintool.py
binman/cbfs_util.py
binman/cmdline.py
binman/control.py
binman/elf.py
binman/entry.py
binman/fip_util.py
binman/fmap_util.py
binman/image.py
binman/main.py
binman/setup.py
binman/state.py
binman/btool/_testing.py
binman/btool/bootgen.py
binman/btool/btool_gzip.py
binman/btool/bzip2.py
binman/btool/cbfstool.py
binman/btool/cst.py
binman/btool/fdt_add_pubkey.py
binman/btool/fdtgrep.py
binman/btool/fiptool.py
binman/btool/futility.py
binman/btool/ifwitool.py
binman/btool/lz4.py
binman/btool/lzma_alone.py
binman/btool/lzop.py
binman/btool/mkeficapsule.py
binman/btool/mkimage.py
binman/btool/openssl.py
binman/btool/xz.py
binman/btool/zstd.py
binman/etype/_testing.py
binman/etype/alternates_fdt.py
binman/etype/atf_bl1.py
binman/etype/atf_bl31.py
binman/etype/atf_fip.py
binman/etype/blob.py
binman/etype/blob_dtb.py
binman/etype/blob_ext.py
binman/etype/blob_ext_list.py
binman/etype/blob_named_by_arg.py
binman/etype/blob_phase.py
binman/etype/cbfs.py
binman/etype/collection.py
binman/etype/cros_ec_rw.py
binman/etype/efi_capsule.py
binman/etype/efi_empty_capsule.py
binman/etype/encrypted.py
binman/etype/fdtmap.py
binman/etype/files.py
binman/etype/fill.py
binman/etype/fit.py
binman/etype/fmap.py
binman/etype/gbb.py
binman/etype/image_header.py
binman/etype/intel_cmc.py
binman/etype/intel_descriptor.py
binman/etype/intel_fit.py
binman/etype/intel_fit_ptr.py
binman/etype/intel_fsp.py
binman/etype/intel_fsp_m.py
binman/etype/intel_fsp_s.py
binman/etype/intel_fsp_t.py
binman/etype/intel_ifwi.py
binman/etype/intel_me.py
binman/etype/intel_mrc.py
binman/etype/intel_refcode.py
binman/etype/intel_vbt.py
binman/etype/intel_vga.py
binman/etype/mkimage.py
binman/etype/null.py
binman/etype/nxp_header_ddrfw.py
binman/etype/nxp_imx8mcst.py
binman/etype/nxp_imx8mimage.py
binman/etype/opensbi.py
binman/etype/powerpc_mpc85xx_bootpg_resetvec.py
binman/etype/pre_load.py
binman/etype/rockchip_tpl.py
binman/etype/scp.py
binman/etype/section.py
binary_manager-0.0.7.dist-info/METADATA
binary_manager-0.0.7.dist-info/WHEEL
binary_manager-0.0.7.dist-info/entry_points.txt
binary_manager-0.0.7.dist-info/top_level.txt
binary_manager-0.0.7.dist-info/RECORD
